README.md
setup.cfg
setup.py
nonsentence/__init__.py
nonsentence.egg-info/PKG-INFO
nonsentence.egg-info/SOURCES.txt
nonsentence.egg-info/dependency_links.txt
nonsentence.egg-info/top_level.txt